[
	{
		"id": 1,
		"phrase": "insurance"
	},
	{
		"id": 2,
		"phrase": "joke"
	},
	{
		"id": 3,
		"phrase": "able"
	},
	{
		"id": 4,
		"phrase": "marvelous"
	},
	{
		"id": 5,
		"phrase": "arch"
	},
	{
		"id": 6,
		"phrase": "delight"
	},
	{
		"id": 7,
		"phrase": "elbow"
	},
	{
		"id": 8,
		"phrase": "free"
	},
	{
		"id": 9,
		"phrase": "follow"
	},
	{
		"id": 10,
		"phrase": "extra-large"
	},
	{
		"id": 11,
		"phrase": "envious"
	},
	{
		"id": 12,
		"phrase": "stupendous"
	},
	{
		"id": 13,
		"phrase": "nice"
	},
	{
		"id": 14,
		"phrase": "blot"
	},
	{
		"id": 15,
		"phrase": "dare"
	},
	{
		"id": 16,
		"phrase": "market"
	},
	{
		"id": 17,
		"phrase": "lying"
	},
	{
		"id": 18,
		"phrase": "undesirable"
	},
	{
		"id": 19,
		"phrase": "seed"
	},
	{
		"id": 20,
		"phrase": "scarf"
	},
	{
		"id": 21,
		"phrase": "straw"
	},
	{
		"id": 22,
		"phrase": "milk"
	},
	{
		"id": 23,
		"phrase": "illustrious"
	},
	{
		"id": 24,
		"phrase": "woman"
	},
	{
		"id": 25,
		"phrase": "night"
	},
	{
		"id": 26,
		"phrase": "moldy"
	},
	{
		"id": 27,
		"phrase": "frightened"
	},
	{
		"id": 28,
		"phrase": "violet"
	},
	{
		"id": 29,
		"phrase": "zany"
	},
	{
		"id": 30,
		"phrase": "plantation"
	},
	{
		"id": 31,
		"phrase": "quill"
	},
	{
		"id": 32,
		"phrase": "confuse"
	},
	{
		"id": 33,
		"phrase": "smiling"
	},
	{
		"id": 34,
		"phrase": "decay"
	},
	{
		"id": 35,
		"phrase": "stereotyped"
	},
	{
		"id": 36,
		"phrase": "reminiscent"
	},
	{
		"id": 37,
		"phrase": "fog"
	},
	{
		"id": 38,
		"phrase": "fine"
	},
	{
		"id": 39,
		"phrase": "joyous"
	},
	{
		"id": 40,
		"phrase": "structure"
	},
	{
		"id": 41,
		"phrase": "suck"
	},
	{
		"id": 42,
		"phrase": "cook"
	},
	{
		"id": 43,
		"phrase": "few"
	},
	{
		"id": 44,
		"phrase": "wholesale"
	},
	{
		"id": 45,
		"phrase": "wire"
	},
	{
		"id": 46,
		"phrase": "replace"
	},
	{
		"id": 47,
		"phrase": "military"
	},
	{
		"id": 48,
		"phrase": "tenuous"
	},
	{
		"id": 49,
		"phrase": "war"
	},
	{
		"id": 50,
		"phrase": "argue"
	},
	{
		"id": 51,
		"phrase": "weather"
	},
	{
		"id": 52,
		"phrase": "quixotic"
	},
	{
		"id": 53,
		"phrase": "yoke"
	},
	{
		"id": 54,
		"phrase": "guarantee"
	},
	{
		"id": 55,
		"phrase": "flashy"
	},
	{
		"id": 56,
		"phrase": "grateful"
	},
	{
		"id": 57,
		"phrase": "horses"
	},
	{
		"id": 58,
		"phrase": "imperfect"
	},
	{
		"id": 59,
		"phrase": "wealth"
	},
	{
		"id": 60,
		"phrase": "marble"
	},
	{
		"id": 61,
		"phrase": "verdant"
	},
	{
		"id": 62,
		"phrase": "drink"
	},
	{
		"id": 63,
		"phrase": "choke"
	},
	{
		"id": 64,
		"phrase": "comfortable"
	},
	{
		"id": 65,
		"phrase": "highfalutin"
	},
	{
		"id": 66,
		"phrase": "underwear"
	},
	{
		"id": 67,
		"phrase": "print"
	},
	{
		"id": 68,
		"phrase": "grotesque"
	},
	{
		"id": 69,
		"phrase": "smart"
	},
	{
		"id": 70,
		"phrase": "doubt"
	},
	{
		"id": 71,
		"phrase": "wanting"
	},
	{
		"id": 72,
		"phrase": "tick"
	},
	{
		"id": 73,
		"phrase": "zippy"
	},
	{
		"id": 74,
		"phrase": "float"
	},
	{
		"id": 75,
		"phrase": "noiseless"
	},
	{
		"id": 76,
		"phrase": "rub"
	},
	{
		"id": 77,
		"phrase": "giant"
	},
	{
		"id": 78,
		"phrase": "step"
	},
	{
		"id": 79,
		"phrase": "writing"
	},
	{
		"id": 80,
		"phrase": "smoggy"
	},
	{
		"id": 81,
		"phrase": "creator"
	},
	{
		"id": 82,
		"phrase": "spiteful"
	},
	{
		"id": 83,
		"phrase": "bolt"
	},
	{
		"id": 84,
		"phrase": "quiet"
	},
	{
		"id": 85,
		"phrase": "grab"
	},
	{
		"id": 86,
		"phrase": "buzz"
	},
	{
		"id": 87,
		"phrase": "continue"
	},
	{
		"id": 88,
		"phrase": "team"
	},
	{
		"id": 89,
		"phrase": "absorbed"
	},
	{
		"id": 90,
		"phrase": "prepare"
	},
	{
		"id": 91,
		"phrase": "scattered"
	},
	{
		"id": 92,
		"phrase": "crowd"
	},
	{
		"id": 93,
		"phrase": "oven"
	},
	{
		"id": 94,
		"phrase": "hour"
	},
	{
		"id": 95,
		"phrase": "cowardly"
	},
	{
		"id": 96,
		"phrase": "boring"
	},
	{
		"id": 97,
		"phrase": "hydrant"
	},
	{
		"id": 98,
		"phrase": "deep"
	},
	{
		"id": 99,
		"phrase": "representative"
	},
	{
		"id": 100,
		"phrase": "symptomatic"
	},
	{
		"id": 101,
		"phrase": "black"
	},
	{
		"id": 102,
		"phrase": "wipe"
	},
	{
		"id": 103,
		"phrase": "soggy"
	},
	{
		"id": 104,
		"phrase": "disappear"
	},
	{
		"id": 105,
		"phrase": "afternoon"
	},
	{
		"id": 106,
		"phrase": "helpful"
	},
	{
		"id": 107,
		"phrase": "fumbling"
	},
	{
		"id": 108,
		"phrase": "sweltering"
	},
	{
		"id": 109,
		"phrase": "inquisitive"
	},
	{
		"id": 110,
		"phrase": "behavior"
	},
	{
		"id": 111,
		"phrase": "stamp"
	},
	{
		"id": 112,
		"phrase": "number"
	},
	{
		"id": 113,
		"phrase": "actor"
	},
	{
		"id": 114,
		"phrase": "discover"
	},
	{
		"id": 115,
		"phrase": "butter"
	},
	{
		"id": 116,
		"phrase": "outrageous"
	},
	{
		"id": 117,
		"phrase": "toothbrush"
	},
	{
		"id": 118,
		"phrase": "station"
	},
	{
		"id": 119,
		"phrase": "connect"
	},
	{
		"id": 120,
		"phrase": "seal"
	},
	{
		"id": 121,
		"phrase": "tidy"
	},
	{
		"id": 122,
		"phrase": "order"
	},
	{
		"id": 123,
		"phrase": "hideous"
	},
	{
		"id": 124,
		"phrase": "self"
	},
	{
		"id": 125,
		"phrase": "depressed"
	},
	{
		"id": 126,
		"phrase": "whole"
	},
	{
		"id": 127,
		"phrase": "account"
	},
	{
		"id": 128,
		"phrase": "curl"
	},
	{
		"id": 129,
		"phrase": "null"
	},
	{
		"id": 130,
		"phrase": "spotty"
	},
	{
		"id": 131,
		"phrase": "giddy"
	},
	{
		"id": 132,
		"phrase": "minute"
	},
	{
		"id": 133,
		"phrase": "water"
	},
	{
		"id": 134,
		"phrase": "appliance"
	},
	{
		"id": 135,
		"phrase": "chalk"
	},
	{
		"id": 136,
		"phrase": "rabid"
	},
	{
		"id": 137,
		"phrase": "unique"
	},
	{
		"id": 138,
		"phrase": "magical"
	},
	{
		"id": 139,
		"phrase": "bushes"
	},
	{
		"id": 140,
		"phrase": "belligerent"
	},
	{
		"id": 141,
		"phrase": "moor"
	},
	{
		"id": 142,
		"phrase": "serious"
	},
	{
		"id": 143,
		"phrase": "majestic"
	},
	{
		"id": 144,
		"phrase": "tacit"
	},
	{
		"id": 145,
		"phrase": "weigh"
	},
	{
		"id": 146,
		"phrase": "stimulating"
	},
	{
		"id": 147,
		"phrase": "pig"
	},
	{
		"id": 148,
		"phrase": "practice"
	},
	{
		"id": 149,
		"phrase": "resonant"
	},
	{
		"id": 150,
		"phrase": "bake"
	},
	{
		"id": 151,
		"phrase": "succinct"
	},
	{
		"id": 152,
		"phrase": "current"
	},
	{
		"id": 153,
		"phrase": "act"
	},
	{
		"id": 154,
		"phrase": "exchange"
	},
	{
		"id": 155,
		"phrase": "swing"
	},
	{
		"id": 156,
		"phrase": "range"
	},
	{
		"id": 157,
		"phrase": "realize"
	},
	{
		"id": 158,
		"phrase": "jobless"
	},
	{
		"id": 159,
		"phrase": "internal"
	},
	{
		"id": 160,
		"phrase": "name"
	},
	{
		"id": 161,
		"phrase": "obscene"
	},
	{
		"id": 162,
		"phrase": "examine"
	},
	{
		"id": 163,
		"phrase": "drab"
	},
	{
		"id": 164,
		"phrase": "chickens"
	},
	{
		"id": 165,
		"phrase": "delicious"
	},
	{
		"id": 166,
		"phrase": "ten"
	},
	{
		"id": 167,
		"phrase": "vagabond"
	},
	{
		"id": 168,
		"phrase": "shave"
	},
	{
		"id": 169,
		"phrase": "hop"
	},
	{
		"id": 170,
		"phrase": "borrow"
	},
	{
		"id": 171,
		"phrase": "acoustic"
	},
	{
		"id": 172,
		"phrase": "fuel"
	},
	{
		"id": 173,
		"phrase": "hospital"
	},
	{
		"id": 174,
		"phrase": "front"
	},
	{
		"id": 175,
		"phrase": "crawl"
	},
	{
		"id": 176,
		"phrase": "preserve"
	},
	{
		"id": 177,
		"phrase": "impartial"
	},
	{
		"id": 178,
		"phrase": "imported"
	},
	{
		"id": 179,
		"phrase": "cactus"
	},
	{
		"id": 180,
		"phrase": "memory"
	},
	{
		"id": 181,
		"phrase": "way"
	},
	{
		"id": 182,
		"phrase": "bless"
	},
	{
		"id": 183,
		"phrase": "suffer"
	},
	{
		"id": 184,
		"phrase": "classy"
	},
	{
		"id": 185,
		"phrase": "escape"
	},
	{
		"id": 186,
		"phrase": "tank"
	},
	{
		"id": 187,
		"phrase": "natural"
	},
	{
		"id": 188,
		"phrase": "expansion"
	},
	{
		"id": 189,
		"phrase": "groovy"
	},
	{
		"id": 190,
		"phrase": "efficient"
	},
	{
		"id": 191,
		"phrase": "knot"
	},
	{
		"id": 192,
		"phrase": "childlike"
	},
	{
		"id": 193,
		"phrase": "thank"
	},
	{
		"id": 194,
		"phrase": "pet"
	},
	{
		"id": 195,
		"phrase": "ambiguous"
	},
	{
		"id": 196,
		"phrase": "skinny"
	},
	{
		"id": 197,
		"phrase": "type"
	},
	{
		"id": 198,
		"phrase": "control"
	},
	{
		"id": 199,
		"phrase": "key"
	},
	{
		"id": 200,
		"phrase": "north"
	},
	{
		"id": 201,
		"phrase": "verse"
	},
	{
		"id": 202,
		"phrase": "bird"
	},
	{
		"id": 203,
		"phrase": "burn"
	},
	{
		"id": 204,
		"phrase": "functional"
	},
	{
		"id": 205,
		"phrase": "multiply"
	},
	{
		"id": 206,
		"phrase": "tie"
	},
	{
		"id": 207,
		"phrase": "soothe"
	},
	{
		"id": 208,
		"phrase": "relax"
	},
	{
		"id": 209,
		"phrase": "talk"
	},
	{
		"id": 210,
		"phrase": "charge"
	},
	{
		"id": 211,
		"phrase": "line"
	},
	{
		"id": 212,
		"phrase": "rule"
	},
	{
		"id": 213,
		"phrase": "mother"
	},
	{
		"id": 214,
		"phrase": "plant"
	},
	{
		"id": 215,
		"phrase": "top"
	},
	{
		"id": 216,
		"phrase": "meaty"
	},
	{
		"id": 217,
		"phrase": "meddle"
	},
	{
		"id": 218,
		"phrase": "enjoy"
	},
	{
		"id": 219,
		"phrase": "crown"
	},
	{
		"id": 220,
		"phrase": "scare"
	},
	{
		"id": 221,
		"phrase": "auspicious"
	},
	{
		"id": 222,
		"phrase": "radiate"
	},
	{
		"id": 223,
		"phrase": "wound"
	},
	{
		"id": 224,
		"phrase": "next"
	},
	{
		"id": 225,
		"phrase": "disagree"
	},
	{
		"id": 226,
		"phrase": "destroy"
	},
	{
		"id": 227,
		"phrase": "tawdry"
	},
	{
		"id": 228,
		"phrase": "substance"
	},
	{
		"id": 229,
		"phrase": "lethal"
	},
	{
		"id": 230,
		"phrase": "jar"
	},
	{
		"id": 231,
		"phrase": "cat"
	},
	{
		"id": 232,
		"phrase": "selective"
	},
	{
		"id": 233,
		"phrase": "whistle"
	},
	{
		"id": 234,
		"phrase": "trees"
	},
	{
		"id": 235,
		"phrase": "coil"
	},
	{
		"id": 236,
		"phrase": "unsightly"
	},
	{
		"id": 237,
		"phrase": "theory"
	},
	{
		"id": 238,
		"phrase": "analyze"
	},
	{
		"id": 239,
		"phrase": "library"
	},
	{
		"id": 240,
		"phrase": "school"
	},
	{
		"id": 241,
		"phrase": "flight"
	},
	{
		"id": 242,
		"phrase": "ticket"
	},
	{
		"id": 243,
		"phrase": "canvas"
	},
	{
		"id": 244,
		"phrase": "fill"
	},
	{
		"id": 245,
		"phrase": "gullible"
	},
	{
		"id": 246,
		"phrase": "foamy"
	},
	{
		"id": 247,
		"phrase": "load"
	},
	{
		"id": 248,
		"phrase": "sparkle"
	},
	{
		"id": 249,
		"phrase": "cloudy"
	},
	{
		"id": 250,
		"phrase": "breakable"
	},
	{
		"id": 251,
		"phrase": "irate"
	},
	{
		"id": 252,
		"phrase": "grain"
	},
	{
		"id": 253,
		"phrase": "arrange"
	},
	{
		"id": 254,
		"phrase": "kick"
	},
	{
		"id": 255,
		"phrase": "hushed"
	},
	{
		"id": 256,
		"phrase": "crate"
	},
	{
		"id": 257,
		"phrase": "icky"
	},
	{
		"id": 258,
		"phrase": "dream"
	},
	{
		"id": 259,
		"phrase": "advise"
	},
	{
		"id": 260,
		"phrase": "division"
	},
	{
		"id": 261,
		"phrase": "didactic"
	},
	{
		"id": 262,
		"phrase": "dapper"
	},
	{
		"id": 263,
		"phrase": "flower"
	},
	{
		"id": 264,
		"phrase": "seat"
	},
	{
		"id": 265,
		"phrase": "son"
	},
	{
		"id": 266,
		"phrase": "compete"
	},
	{
		"id": 267,
		"phrase": "panoramic"
	},
	{
		"id": 268,
		"phrase": "history"
	},
	{
		"id": 269,
		"phrase": "immense"
	},
	{
		"id": 270,
		"phrase": "girl"
	},
	{
		"id": 271,
		"phrase": "peck"
	},
	{
		"id": 272,
		"phrase": "cure"
	},
	{
		"id": 273,
		"phrase": "claim"
	},
	{
		"id": 274,
		"phrase": "cushion"
	},
	{
		"id": 275,
		"phrase": "page"
	},
	{
		"id": 276,
		"phrase": "discovery"
	},
	{
		"id": 277,
		"phrase": "mine"
	},
	{
		"id": 278,
		"phrase": "onerous"
	},
	{
		"id": 279,
		"phrase": "add"
	},
	{
		"id": 280,
		"phrase": "note"
	},
	{
		"id": 281,
		"phrase": "queen"
	},
	{
		"id": 282,
		"phrase": "women"
	},
	{
		"id": 283,
		"phrase": "loaf"
	},
	{
		"id": 284,
		"phrase": "secretive"
	},
	{
		"id": 285,
		"phrase": "tickle"
	},
	{
		"id": 286,
		"phrase": "dynamic"
	},
	{
		"id": 287,
		"phrase": "gratis"
	},
	{
		"id": 288,
		"phrase": "reading"
	},
	{
		"id": 289,
		"phrase": "store"
	},
	{
		"id": 290,
		"phrase": "infamous"
	},
	{
		"id": 291,
		"phrase": "excite"
	},
	{
		"id": 292,
		"phrase": "steady"
	},
	{
		"id": 293,
		"phrase": "end"
	},
	{
		"id": 294,
		"phrase": "birthday"
	},
	{
		"id": 295,
		"phrase": "bow"
	},
	{
		"id": 296,
		"phrase": "test"
	},
	{
		"id": 297,
		"phrase": "pleasure"
	},
	{
		"id": 298,
		"phrase": "brainy"
	},
	{
		"id": 299,
		"phrase": "ask"
	},
	{
		"id": 300,
		"phrase": "subdued"
	},
	{
		"id": 301,
		"phrase": "aromatic"
	},
	{
		"id": 302,
		"phrase": "employ"
	},
	{
		"id": 303,
		"phrase": "brawny"
	},
	{
		"id": 304,
		"phrase": "complete"
	},
	{
		"id": 305,
		"phrase": "office"
	},
	{
		"id": 306,
		"phrase": "erect"
	},
	{
		"id": 307,
		"phrase": "intelligent"
	},
	{
		"id": 308,
		"phrase": "thumb"
	},
	{
		"id": 309,
		"phrase": "offer"
	},
	{
		"id": 310,
		"phrase": "teeny"
	},
	{
		"id": 311,
		"phrase": "hurry"
	},
	{
		"id": 312,
		"phrase": "shame"
	},
	{
		"id": 313,
		"phrase": "fool"
	},
	{
		"id": 314,
		"phrase": "acid"
	},
	{
		"id": 315,
		"phrase": "closed"
	},
	{
		"id": 316,
		"phrase": "alleged"
	},
	{
		"id": 317,
		"phrase": "enormous"
	},
	{
		"id": 318,
		"phrase": "square"
	},
	{
		"id": 319,
		"phrase": "ajar"
	},
	{
		"id": 320,
		"phrase": "high"
	},
	{
		"id": 321,
		"phrase": "belong"
	},
	{
		"id": 322,
		"phrase": "giraffe"
	},
	{
		"id": 323,
		"phrase": "size"
	},
	{
		"id": 324,
		"phrase": "bear"
	},
	{
		"id": 325,
		"phrase": "bells"
	},
	{
		"id": 326,
		"phrase": "penitent"
	},
	{
		"id": 327,
		"phrase": "efficacious"
	},
	{
		"id": 328,
		"phrase": "vein"
	},
	{
		"id": 329,
		"phrase": "glass"
	},
	{
		"id": 330,
		"phrase": "doctor"
	},
	{
		"id": 331,
		"phrase": "smooth"
	},
	{
		"id": 332,
		"phrase": "typical"
	},
	{
		"id": 333,
		"phrase": "crook"
	},
	{
		"id": 334,
		"phrase": "rural"
	},
	{
		"id": 335,
		"phrase": "prickly"
	},
	{
		"id": 336,
		"phrase": "temporary"
	},
	{
		"id": 337,
		"phrase": "friction"
	},
	{
		"id": 338,
		"phrase": "basin"
	},
	{
		"id": 339,
		"phrase": "obsequious"
	},
	{
		"id": 340,
		"phrase": "polite"
	},
	{
		"id": 341,
		"phrase": "mere"
	},
	{
		"id": 342,
		"phrase": "expert"
	},
	{
		"id": 343,
		"phrase": "selection"
	},
	{
		"id": 344,
		"phrase": "kill"
	},
	{
		"id": 345,
		"phrase": "fat"
	},
	{
		"id": 346,
		"phrase": "trade"
	},
	{
		"id": 347,
		"phrase": "puzzled"
	},
	{
		"id": 348,
		"phrase": "half"
	},
	{
		"id": 349,
		"phrase": "lean"
	},
	{
		"id": 350,
		"phrase": "treatment"
	},
	{
		"id": 351,
		"phrase": "handsomely"
	},
	{
		"id": 352,
		"phrase": "yellow"
	},
	{
		"id": 353,
		"phrase": "shy"
	},
	{
		"id": 354,
		"phrase": "delicate"
	},
	{
		"id": 355,
		"phrase": "growth"
	},
	{
		"id": 356,
		"phrase": "disturbed"
	},
	{
		"id": 357,
		"phrase": "telling"
	},
	{
		"id": 358,
		"phrase": "ubiquitous"
	},
	{
		"id": 359,
		"phrase": "rhyme"
	},
	{
		"id": 360,
		"phrase": "money"
	},
	{
		"id": 361,
		"phrase": "evanescent"
	},
	{
		"id": 362,
		"phrase": "metal"
	},
	{
		"id": 363,
		"phrase": "cheese"
	},
	{
		"id": 364,
		"phrase": "birds"
	},
	{
		"id": 365,
		"phrase": "fair"
	},
	{
		"id": 366,
		"phrase": "object"
	},
	{
		"id": 367,
		"phrase": "truck"
	},
	{
		"id": 368,
		"phrase": "deliver"
	},
	{
		"id": 369,
		"phrase": "cake"
	},
	{
		"id": 370,
		"phrase": "black-and-white"
	},
	{
		"id": 371,
		"phrase": "new"
	},
	{
		"id": 372,
		"phrase": "march"
	},
	{
		"id": 373,
		"phrase": "tremble"
	},
	{
		"id": 374,
		"phrase": "one"
	},
	{
		"id": 375,
		"phrase": "gaze"
	},
	{
		"id": 376,
		"phrase": "stone"
	},
	{
		"id": 377,
		"phrase": "healthy"
	},
	{
		"id": 378,
		"phrase": "change"
	},
	{
		"id": 379,
		"phrase": "rhythm"
	},
	{
		"id": 380,
		"phrase": "uncle"
	},
	{
		"id": 381,
		"phrase": "five"
	},
	{
		"id": 382,
		"phrase": "behave"
	},
	{
		"id": 383,
		"phrase": "loutish"
	},
	{
		"id": 384,
		"phrase": "nimble"
	},
	{
		"id": 385,
		"phrase": "puffy"
	},
	{
		"id": 386,
		"phrase": "assorted"
	},
	{
		"id": 387,
		"phrase": "sack"
	},
	{
		"id": 388,
		"phrase": "organic"
	},
	{
		"id": 389,
		"phrase": "worried"
	},
	{
		"id": 390,
		"phrase": "utopian"
	},
	{
		"id": 391,
		"phrase": "offbeat"
	},
	{
		"id": 392,
		"phrase": "macabre"
	},
	{
		"id": 393,
		"phrase": "unhealthy"
	},
	{
		"id": 394,
		"phrase": "vacation"
	},
	{
		"id": 395,
		"phrase": "expensive"
	},
	{
		"id": 396,
		"phrase": "trouble"
	},
	{
		"id": 397,
		"phrase": "place"
	},
	{
		"id": 398,
		"phrase": "beef"
	},
	{
		"id": 399,
		"phrase": "desert"
	},
	{
		"id": 400,
		"phrase": "blushing"
	},
	{
		"id": 401,
		"phrase": "competition"
	},
	{
		"id": 402,
		"phrase": "position"
	},
	{
		"id": 403,
		"phrase": "visit"
	},
	{
		"id": 404,
		"phrase": "frog"
	},
	{
		"id": 405,
		"phrase": "purring"
	},
	{
		"id": 406,
		"phrase": "exist"
	},
	{
		"id": 407,
		"phrase": "discussion"
	},
	{
		"id": 408,
		"phrase": "amuse"
	},
	{
		"id": 409,
		"phrase": "doubtful"
	},
	{
		"id": 410,
		"phrase": "calculating"
	},
	{
		"id": 411,
		"phrase": "appear"
	},
	{
		"id": 412,
		"phrase": "wide"
	},
	{
		"id": 413,
		"phrase": "empty"
	},
	{
		"id": 414,
		"phrase": "uptight"
	},
	{
		"id": 415,
		"phrase": "shut"
	},
	{
		"id": 416,
		"phrase": "pinch"
	},
	{
		"id": 417,
		"phrase": "occur"
	},
	{
		"id": 418,
		"phrase": "cannon"
	},
	{
		"id": 419,
		"phrase": "cemetery"
	},
	{
		"id": 420,
		"phrase": "cellar"
	},
	{
		"id": 421,
		"phrase": "celery"
	},
	{
		"id": 422,
		"phrase": "calendar"
	},
	{
		"id": 423,
		"phrase": "elated"
	},
	{
		"id": 424,
		"phrase": "guarded"
	},
	{
		"id": 425,
		"phrase": "heady"
	},
	{
		"id": 426,
		"phrase": "nebulous"
	},
	{
		"id": 427,
		"phrase": "neat"
	},
	{
		"id": 428,
		"phrase": "descriptive"
	},
	{
		"id": 429,
		"phrase": "weary"
	},
	{
		"id": 430,
		"phrase": "surprise"
	},
	{
		"id": 431,
		"phrase": "embarrassed"
	},
	{
		"id": 432,
		"phrase": "venomous"
	},
	{
		"id": 433,
		"phrase": "melodic"
	},
	{
		"id": 434,
		"phrase": "grieving"
	},
	{
		"id": 435,
		"phrase": "haunt"
	},
	{
		"id": 436,
		"phrase": "crush"
	},
	{
		"id": 437,
		"phrase": "year"
	},
	{
		"id": 438,
		"phrase": "changeable"
	},
	{
		"id": 439,
		"phrase": "club"
	},
	{
		"id": 440,
		"phrase": "food"
	},
	{
		"id": 441,
		"phrase": "scarecrow"
	},
	{
		"id": 442,
		"phrase": "hands"
	},
	{
		"id": 443,
		"phrase": "repeat"
	},
	{
		"id": 444,
		"phrase": "ants"
	},
	{
		"id": 445,
		"phrase": "laughable"
	},
	{
		"id": 446,
		"phrase": "form"
	},
	{
		"id": 447,
		"phrase": "snails"
	},
	{
		"id": 448,
		"phrase": "mate"
	},
	{
		"id": 449,
		"phrase": "parcel"
	},
	{
		"id": 450,
		"phrase": "productive"
	},
	{
		"id": 451,
		"phrase": "glow"
	},
	{
		"id": 452,
		"phrase": "amount"
	},
	{
		"id": 453,
		"phrase": "fallacious"
	},
	{
		"id": 454,
		"phrase": "materialistic"
	},
	{
		"id": 455,
		"phrase": "apathetic"
	},
	{
		"id": 456,
		"phrase": "paddle"
	},
	{
		"id": 457,
		"phrase": "evasive"
	},
	{
		"id": 458,
		"phrase": "ultra"
	},
	{
		"id": 459,
		"phrase": "compare"
	},
	{
		"id": 460,
		"phrase": "cynical"
	},
	{
		"id": 461,
		"phrase": "rampant"
	},
	{
		"id": 462,
		"phrase": "drip"
	},
	{
		"id": 463,
		"phrase": "straight"
	},
	{
		"id": 464,
		"phrase": "cumbersome"
	},
	{
		"id": 465,
		"phrase": "pause"
	},
	{
		"id": 466,
		"phrase": "arrogant"
	},
	{
		"id": 467,
		"phrase": "harbor"
	},
	{
		"id": 468,
		"phrase": "fold"
	},
	{
		"id": 469,
		"phrase": "overrated"
	},
	{
		"id": 470,
		"phrase": "squalid"
	},
	{
		"id": 471,
		"phrase": "frighten"
	},
	{
		"id": 472,
		"phrase": "exultant"
	},
	{
		"id": 473,
		"phrase": "finicky"
	},
	{
		"id": 474,
		"phrase": "husky"
	},
	{
		"id": 475,
		"phrase": "picayune"
	},
	{
		"id": 476,
		"phrase": "waggish"
	},
	{
		"id": 477,
		"phrase": "children"
	},
	{
		"id": 478,
		"phrase": "touch"
	},
	{
		"id": 479,
		"phrase": "condition"
	},
	{
		"id": 480,
		"phrase": "squealing"
	},
	{
		"id": 481,
		"phrase": "magnificent"
	},
	{
		"id": 482,
		"phrase": "eager"
	},
	{
		"id": 483,
		"phrase": "art"
	},
	{
		"id": 484,
		"phrase": "frame"
	},
	{
		"id": 485,
		"phrase": "well-off"
	},
	{
		"id": 486,
		"phrase": "giants"
	},
	{
		"id": 487,
		"phrase": "willing"
	},
	{
		"id": 488,
		"phrase": "harass"
	},
	{
		"id": 489,
		"phrase": "stare"
	},
	{
		"id": 490,
		"phrase": "thrill"
	},
	{
		"id": 491,
		"phrase": "stream"
	},
	{
		"id": 492,
		"phrase": "stem"
	},
	{
		"id": 493,
		"phrase": "ashamed"
	},
	{
		"id": 494,
		"phrase": "ad hoc"
	},
	{
		"id": 495,
		"phrase": "ground"
	},
	{
		"id": 496,
		"phrase": "locket"
	},
	{
		"id": 497,
		"phrase": "wind"
	},
	{
		"id": 498,
		"phrase": "ethereal"
	},
	{
		"id": 499,
		"phrase": "approval"
	},
	{
		"id": 500,
		"phrase": "noxious"
	},
	{
		"id": 501,
		"phrase": "sassy"
	},
	{
		"id": 502,
		"phrase": "nutritious"
	},
	{
		"id": 503,
		"phrase": "listen"
	},
	{
		"id": 504,
		"phrase": "spill"
	},
	{
		"id": 505,
		"phrase": "ocean"
	},
	{
		"id": 506,
		"phrase": "voice"
	},
	{
		"id": 507,
		"phrase": "scared"
	},
	{
		"id": 508,
		"phrase": "stormy"
	},
	{
		"id": 509,
		"phrase": "tent"
	},
	{
		"id": 510,
		"phrase": "fork"
	},
	{
		"id": 511,
		"phrase": "chunky"
	},
	{
		"id": 512,
		"phrase": "dislike"
	},
	{
		"id": 513,
		"phrase": "sweet"
	},
	{
		"id": 514,
		"phrase": "wrong"
	},
	{
		"id": 515,
		"phrase": "humorous"
	},
	{
		"id": 516,
		"phrase": "addicted"
	},
	{
		"id": 517,
		"phrase": "actually"
	},
	{
		"id": 518,
		"phrase": "innate"
	},
	{
		"id": 519,
		"phrase": "enthusiastic"
	},
	{
		"id": 520,
		"phrase": "marry"
	},
	{
		"id": 521,
		"phrase": "hook"
	},
	{
		"id": 522,
		"phrase": "amusing"
	},
	{
		"id": 523,
		"phrase": "old-fashioned"
	},
	{
		"id": 524,
		"phrase": "rifle"
	},
	{
		"id": 525,
		"phrase": "foot"
	},
	{
		"id": 526,
		"phrase": "recondite"
	},
	{
		"id": 527,
		"phrase": "near"
	},
	{
		"id": 528,
		"phrase": "pull"
	},
	{
		"id": 529,
		"phrase": "trap"
	},
	{
		"id": 530,
		"phrase": "channel"
	},
	{
		"id": 531,
		"phrase": "mom"
	},
	{
		"id": 532,
		"phrase": "writer"
	},
	{
		"id": 533,
		"phrase": "permissible"
	},
	{
		"id": 534,
		"phrase": "clover"
	},
	{
		"id": 535,
		"phrase": "conscious"
	},
	{
		"id": 536,
		"phrase": "long-term"
	},
	{
		"id": 537,
		"phrase": "fruit"
	},
	{
		"id": 538,
		"phrase": "annoy"
	},
	{
		"id": 539,
		"phrase": "detailed"
	},
	{
		"id": 540,
		"phrase": "tree"
	},
	{
		"id": 541,
		"phrase": "look"
	},
	{
		"id": 542,
		"phrase": "dysfunctional"
	},
	{
		"id": 543,
		"phrase": "nervous"
	},
	{
		"id": 544,
		"phrase": "dress"
	},
	{
		"id": 545,
		"phrase": "destruction"
	},
	{
		"id": 546,
		"phrase": "sniff"
	},
	{
		"id": 547,
		"phrase": "trip"
	},
	{
		"id": 548,
		"phrase": "observant"
	},
	{
		"id": 549,
		"phrase": "unsuitable"
	},
	{
		"id": 550,
		"phrase": "announce"
	},
	{
		"id": 551,
		"phrase": "foregoing"
	},
	{
		"id": 552,
		"phrase": "crack"
	},
	{
		"id": 553,
		"phrase": "busy"
	},
	{
		"id": 554,
		"phrase": "quirky"
	},
	{
		"id": 555,
		"phrase": "shirt"
	},
	{
		"id": 556,
		"phrase": "lonely"
	},
	{
		"id": 557,
		"phrase": "mice"
	},
	{
		"id": 558,
		"phrase": "sulky"
	},
	{
		"id": 559,
		"phrase": "value"
	},
	{
		"id": 560,
		"phrase": "expect"
	},
	{
		"id": 561,
		"phrase": "day"
	},
	{
		"id": 562,
		"phrase": "duck"
	},
	{
		"id": 563,
		"phrase": "literate"
	},
	{
		"id": 564,
		"phrase": "collar"
	},
	{
		"id": 565,
		"phrase": "texture"
	},
	{
		"id": 566,
		"phrase": "angle"
	},
	{
		"id": 567,
		"phrase": "lunchroom"
	},
	{
		"id": 568,
		"phrase": "overflow"
	},
	{
		"id": 569,
		"phrase": "lighten"
	},
	{
		"id": 570,
		"phrase": "rake"
	},
	{
		"id": 571,
		"phrase": "science"
	},
	{
		"id": 572,
		"phrase": "unwritten"
	},
	{
		"id": 573,
		"phrase": "wry"
	},
	{
		"id": 574,
		"phrase": "whine"
	},
	{
		"id": 575,
		"phrase": "staking"
	},
	{
		"id": 576,
		"phrase": "volatile"
	},
	{
		"id": 577,
		"phrase": "ghost"
	},
	{
		"id": 578,
		"phrase": "earth"
	},
	{
		"id": 579,
		"phrase": "habitual"
	},
	{
		"id": 580,
		"phrase": "gaping"
	},
	{
		"id": 581,
		"phrase": "little"
	},
	{
		"id": 582,
		"phrase": "company"
	},
	{
		"id": 583,
		"phrase": "future"
	},
	{
		"id": 584,
		"phrase": "chop"
	},
	{
		"id": 585,
		"phrase": "versed"
	},
	{
		"id": 586,
		"phrase": "copper"
	},
	{
		"id": 587,
		"phrase": "divide"
	},
	{
		"id": 588,
		"phrase": "servant"
	},
	{
		"id": 589,
		"phrase": "roll"
	},
	{
		"id": 590,
		"phrase": "disarm"
	},
	{
		"id": 591,
		"phrase": "animated"
	},
	{
		"id": 592,
		"phrase": "periodic"
	},
	{
		"id": 593,
		"phrase": "unable"
	},
	{
		"id": 594,
		"phrase": "graceful"
	},
	{
		"id": 595,
		"phrase": "parallel"
	},
	{
		"id": 596,
		"phrase": "obese"
	},
	{
		"id": 597,
		"phrase": "approve"
	},
	{
		"id": 598,
		"phrase": "ray"
	},
	{
		"id": 599,
		"phrase": "arithmetic"
	},
	{
		"id": 600,
		"phrase": "minister"
	},
	{
		"id": 601,
		"phrase": "face"
	},
	{
		"id": 602,
		"phrase": "kind"
	},
	{
		"id": 603,
		"phrase": "tasteless"
	},
	{
		"id": 604,
		"phrase": "gruesome"
	},
	{
		"id": 605,
		"phrase": "ball"
	},
	{
		"id": 606,
		"phrase": "cream"
	},
	{
		"id": 607,
		"phrase": "blue-eyed"
	},
	{
		"id": 608,
		"phrase": "ill-fated"
	},
	{
		"id": 609,
		"phrase": "squeamish"
	},
	{
		"id": 610,
		"phrase": "gainful"
	},
	{
		"id": 611,
		"phrase": "thin"
	},
	{
		"id": 612,
		"phrase": "call"
	},
	{
		"id": 613,
		"phrase": "axiomatic"
	},
	{
		"id": 614,
		"phrase": "fix"
	},
	{
		"id": 615,
		"phrase": "useless"
	},
	{
		"id": 616,
		"phrase": "magenta"
	},
	{
		"id": 617,
		"phrase": "rotten"
	},
	{
		"id": 618,
		"phrase": "sticky"
	},
	{
		"id": 619,
		"phrase": "snow"
	},
	{
		"id": 620,
		"phrase": "energetic"
	},
	{
		"id": 621,
		"phrase": "tearful"
	},
	{
		"id": 622,
		"phrase": "pizzas"
	},
	{
		"id": 623,
		"phrase": "furtive"
	},
	{
		"id": 624,
		"phrase": "educated"
	},
	{
		"id": 625,
		"phrase": "rabbit"
	},
	{
		"id": 626,
		"phrase": "receive"
	},
	{
		"id": 627,
		"phrase": "tongue"
	},
	{
		"id": 628,
		"phrase": "wretched"
	},
	{
		"id": 629,
		"phrase": "cart"
	},
	{
		"id": 630,
		"phrase": "expand"
	},
	{
		"id": 631,
		"phrase": "powerful"
	},
	{
		"id": 632,
		"phrase": "flawless"
	},
	{
		"id": 633,
		"phrase": "mature"
	},
	{
		"id": 634,
		"phrase": "mute"
	},
	{
		"id": 635,
		"phrase": "warlike"
	},
	{
		"id": 636,
		"phrase": "soap"
	},
	{
		"id": 637,
		"phrase": "angry"
	},
	{
		"id": 638,
		"phrase": "decorate"
	},
	{
		"id": 639,
		"phrase": "stick"
	},
	{
		"id": 640,
		"phrase": "juice"
	},
	{
		"id": 641,
		"phrase": "snobbish"
	},
	{
		"id": 642,
		"phrase": "luxuriant"
	},
	{
		"id": 643,
		"phrase": "bucket"
	},
	{
		"id": 644,
		"phrase": "berry"
	},
	{
		"id": 645,
		"phrase": "respect"
	},
	{
		"id": 646,
		"phrase": "truculent"
	},
	{
		"id": 647,
		"phrase": "tremendous"
	},
	{
		"id": 648,
		"phrase": "impolite"
	},
	{
		"id": 649,
		"phrase": "greedy"
	},
	{
		"id": 650,
		"phrase": "lush"
	},
	{
		"id": 651,
		"phrase": "disagreeable"
	},
	{
		"id": 652,
		"phrase": "trace"
	},
	{
		"id": 653,
		"phrase": "crime"
	},
	{
		"id": 654,
		"phrase": "boil"
	},
	{
		"id": 655,
		"phrase": "meek"
	},
	{
		"id": 656,
		"phrase": "paltry"
	},
	{
		"id": 657,
		"phrase": "boot"
	},
	{
		"id": 658,
		"phrase": "labored"
	},
	{
		"id": 659,
		"phrase": "spooky"
	},
	{
		"id": 660,
		"phrase": "chubby"
	},
	{
		"id": 661,
		"phrase": "absurd"
	},
	{
		"id": 662,
		"phrase": "dad"
	},
	{
		"id": 663,
		"phrase": "scribble"
	},
	{
		"id": 664,
		"phrase": "abrasive"
	},
	{
		"id": 665,
		"phrase": "crow"
	},
	{
		"id": 666,
		"phrase": "sort"
	},
	{
		"id": 667,
		"phrase": "boiling"
	},
	{
		"id": 668,
		"phrase": "average"
	},
	{
		"id": 669,
		"phrase": "endurable"
	},
	{
		"id": 670,
		"phrase": "trite"
	},
	{
		"id": 671,
		"phrase": "miscreant"
	},
	{
		"id": 672,
		"phrase": "answer"
	},
	{
		"id": 673,
		"phrase": "room"
	},
	{
		"id": 674,
		"phrase": "strap"
	},
	{
		"id": 675,
		"phrase": "truthful"
	},
	{
		"id": 676,
		"phrase": "concerned"
	},
	{
		"id": 677,
		"phrase": "troubled"
	},
	{
		"id": 678,
		"phrase": "stuff"
	},
	{
		"id": 679,
		"phrase": "last"
	},
	{
		"id": 680,
		"phrase": "melted"
	},
	{
		"id": 681,
		"phrase": "spiky"
	},
	{
		"id": 682,
		"phrase": "hypnotic"
	},
	{
		"id": 683,
		"phrase": "unpack"
	},
	{
		"id": 684,
		"phrase": "clear"
	},
	{
		"id": 685,
		"phrase": "deeply"
	},
	{
		"id": 686,
		"phrase": "erratic"
	},
	{
		"id": 687,
		"phrase": "governor"
	},
	{
		"id": 688,
		"phrase": "border"
	},
	{
		"id": 689,
		"phrase": "physical"
	},
	{
		"id": 690,
		"phrase": "abounding"
	},
	{
		"id": 691,
		"phrase": "six"
	},
	{
		"id": 692,
		"phrase": "retire"
	},
	{
		"id": 693,
		"phrase": "understood"
	},
	{
		"id": 694,
		"phrase": "cause"
	},
	{
		"id": 695,
		"phrase": "boat"
	},
	{
		"id": 696,
		"phrase": "deer"
	},
	{
		"id": 697,
		"phrase": "shock"
	},
	{
		"id": 698,
		"phrase": "knock"
	},
	{
		"id": 699,
		"phrase": "stupid"
	},
	{
		"id": 700,
		"phrase": "scrape"
	},
	{
		"id": 701,
		"phrase": "development"
	},
	{
		"id": 702,
		"phrase": "planes"
	},
	{
		"id": 703,
		"phrase": "needle"
	},
	{
		"id": 704,
		"phrase": "savory"
	},
	{
		"id": 705,
		"phrase": "wreck"
	},
	{
		"id": 706,
		"phrase": "notebook"
	},
	{
		"id": 707,
		"phrase": "sweater"
	},
	{
		"id": 708,
		"phrase": "disapprove"
	},
	{
		"id": 709,
		"phrase": "park"
	},
	{
		"id": 710,
		"phrase": "observation"
	},
	{
		"id": 711,
		"phrase": "cattle"
	},
	{
		"id": 712,
		"phrase": "reply"
	},
	{
		"id": 713,
		"phrase": "swift"
	},
	{
		"id": 714,
		"phrase": "painstaking"
	},
	{
		"id": 715,
		"phrase": "wriggle"
	},
	{
		"id": 716,
		"phrase": "deserted"
	},
	{
		"id": 717,
		"phrase": "pollution"
	},
	{
		"id": 718,
		"phrase": "imminent"
	},
	{
		"id": 719,
		"phrase": "sable"
	},
	{
		"id": 720,
		"phrase": "cup"
	},
	{
		"id": 721,
		"phrase": "nostalgic"
	},
	{
		"id": 722,
		"phrase": "air"
	},
	{
		"id": 723,
		"phrase": "songs"
	},
	{
		"id": 724,
		"phrase": "fancy"
	},
	{
		"id": 725,
		"phrase": "nest"
	},
	{
		"id": 726,
		"phrase": "nose"
	},
	{
		"id": 727,
		"phrase": "annoyed"
	},
	{
		"id": 728,
		"phrase": "unusual"
	},
	{
		"id": 729,
		"phrase": "summer"
	},
	{
		"id": 730,
		"phrase": "steam"
	},
	{
		"id": 731,
		"phrase": "run"
	},
	{
		"id": 732,
		"phrase": "crowded"
	},
	{
		"id": 733,
		"phrase": "pointless"
	},
	{
		"id": 734,
		"phrase": "voracious"
	},
	{
		"id": 735,
		"phrase": "spiritual"
	},
	{
		"id": 736,
		"phrase": "business"
	},
	{
		"id": 737,
		"phrase": "flap"
	},
	{
		"id": 738,
		"phrase": "torpid"
	},
	{
		"id": 739,
		"phrase": "wren"
	},
	{
		"id": 740,
		"phrase": "righteous"
	},
	{
		"id": 741,
		"phrase": "daffy"
	},
	{
		"id": 742,
		"phrase": "quick"
	},
	{
		"id": 743,
		"phrase": "daughter"
	},
	{
		"id": 744,
		"phrase": "ruin"
	},
	{
		"id": 745,
		"phrase": "elegant"
	},
	{
		"id": 746,
		"phrase": "sea"
	},
	{
		"id": 747,
		"phrase": "slim"
	},
	{
		"id": 748,
		"phrase": "numberless"
	},
	{
		"id": 749,
		"phrase": "glue"
	},
	{
		"id": 750,
		"phrase": "tumble"
	},
	{
		"id": 751,
		"phrase": "unused"
	},
	{
		"id": 752,
		"phrase": "measly"
	},
	{
		"id": 753,
		"phrase": "push"
	},
	{
		"id": 754,
		"phrase": "hysterical"
	},
	{
		"id": 755,
		"phrase": "well-to-do"
	},
	{
		"id": 756,
		"phrase": "sign"
	},
	{
		"id": 757,
		"phrase": "cracker"
	},
	{
		"id": 758,
		"phrase": "wave"
	},
	{
		"id": 759,
		"phrase": "phobic"
	},
	{
		"id": 760,
		"phrase": "wicked"
	},
	{
		"id": 761,
		"phrase": "humdrum"
	},
	{
		"id": 762,
		"phrase": "hapless"
	},
	{
		"id": 763,
		"phrase": "shade"
	},
	{
		"id": 764,
		"phrase": "huge"
	},
	{
		"id": 765,
		"phrase": "noise"
	},
	{
		"id": 766,
		"phrase": "known"
	},
	{
		"id": 767,
		"phrase": "list"
	},
	{
		"id": 768,
		"phrase": "prefer"
	},
	{
		"id": 769,
		"phrase": "horrible"
	},
	{
		"id": 770,
		"phrase": "adventurous"
	},
	{
		"id": 771,
		"phrase": "rob"
	},
	{
		"id": 772,
		"phrase": "hobbies"
	},
	{
		"id": 773,
		"phrase": "plough"
	},
	{
		"id": 774,
		"phrase": "decisive"
	},
	{
		"id": 775,
		"phrase": "exciting"
	},
	{
		"id": 776,
		"phrase": "teeth"
	},
	{
		"id": 777,
		"phrase": "oceanic"
	},
	{
		"id": 778,
		"phrase": "handsome"
	},
	{
		"id": 779,
		"phrase": "testy"
	},
	{
		"id": 780,
		"phrase": "rate"
	},
	{
		"id": 781,
		"phrase": "plastic"
	},
	{
		"id": 782,
		"phrase": "colossal"
	},
	{
		"id": 783,
		"phrase": "first"
	},
	{
		"id": 784,
		"phrase": "apparel"
	},
	{
		"id": 785,
		"phrase": "corn"
	},
	{
		"id": 786,
		"phrase": "command"
	},
	{
		"id": 787,
		"phrase": "false"
	},
	{
		"id": 788,
		"phrase": "shocking"
	},
	{
		"id": 789,
		"phrase": "increase"
	},
	{
		"id": 790,
		"phrase": "clap"
	},
	{
		"id": 791,
		"phrase": "unarmed"
	},
	{
		"id": 792,
		"phrase": "carpenter"
	},
	{
		"id": 793,
		"phrase": "ludicrous"
	},
	{
		"id": 794,
		"phrase": "valuable"
	},
	{
		"id": 795,
		"phrase": "adamant"
	},
	{
		"id": 796,
		"phrase": "toe"
	},
	{
		"id": 797,
		"phrase": "blood"
	},
	{
		"id": 798,
		"phrase": "pigs"
	},
	{
		"id": 799,
		"phrase": "mundane"
	},
	{
		"id": 800,
		"phrase": "discreet"
	},
	{
		"id": 801,
		"phrase": "iron"
	},
	{
		"id": 802,
		"phrase": "spiders"
	},
	{
		"id": 803,
		"phrase": "watch"
	},
	{
		"id": 804,
		"phrase": "jittery"
	},
	{
		"id": 805,
		"phrase": "pickle"
	},
	{
		"id": 806,
		"phrase": "damp"
	},
	{
		"id": 807,
		"phrase": "awake"
	},
	{
		"id": 808,
		"phrase": "public"
	},
	{
		"id": 809,
		"phrase": "steep"
	},
	{
		"id": 810,
		"phrase": "share"
	},
	{
		"id": 811,
		"phrase": "outgoing"
	},
	{
		"id": 812,
		"phrase": "apparatus"
	},
	{
		"id": 813,
		"phrase": "bumpy"
	},
	{
		"id": 814,
		"phrase": "astonishing"
	},
	{
		"id": 815,
		"phrase": "shake"
	},
	{
		"id": 816,
		"phrase": "unequaled"
	},
	{
		"id": 817,
		"phrase": "idea"
	},
	{
		"id": 818,
		"phrase": "bed"
	},
	{
		"id": 819,
		"phrase": "agreement"
	},
	{
		"id": 820,
		"phrase": "army"
	},
	{
		"id": 821,
		"phrase": "mushy"
	},
	{
		"id": 822,
		"phrase": "panicky"
	},
	{
		"id": 823,
		"phrase": "knowing"
	},
	{
		"id": 824,
		"phrase": "ancient"
	},
	{
		"id": 825,
		"phrase": "uttermost"
	},
	{
		"id": 826,
		"phrase": "clip"
	},
	{
		"id": 827,
		"phrase": "lacking"
	},
	{
		"id": 828,
		"phrase": "rabbits"
	},
	{
		"id": 829,
		"phrase": "tasteful"
	},
	{
		"id": 830,
		"phrase": "kneel"
	},
	{
		"id": 831,
		"phrase": "bustling"
	},
	{
		"id": 832,
		"phrase": "flowery"
	},
	{
		"id": 833,
		"phrase": "detail"
	},
	{
		"id": 834,
		"phrase": "bike"
	},
	{
		"id": 835,
		"phrase": "owe"
	},
	{
		"id": 836,
		"phrase": "massive"
	},
	{
		"id": 837,
		"phrase": "glistening"
	},
	{
		"id": 838,
		"phrase": "jeans"
	},
	{
		"id": 839,
		"phrase": "wacky"
	},
	{
		"id": 840,
		"phrase": "baseball"
	},
	{
		"id": 841,
		"phrase": "miss"
	},
	{
		"id": 842,
		"phrase": "spicy"
	},
	{
		"id": 843,
		"phrase": "abiding"
	},
	{
		"id": 844,
		"phrase": "introduce"
	},
	{
		"id": 845,
		"phrase": "hang"
	},
	{
		"id": 846,
		"phrase": "oafish"
	},
	{
		"id": 847,
		"phrase": "perform"
	},
	{
		"id": 848,
		"phrase": "scale"
	},
	{
		"id": 849,
		"phrase": "sneaky"
	},
	{
		"id": 850,
		"phrase": "vanish"
	},
	{
		"id": 851,
		"phrase": "reach"
	},
	{
		"id": 852,
		"phrase": "precede"
	},
	{
		"id": 853,
		"phrase": "two"
	},
	{
		"id": 854,
		"phrase": "flimsy"
	},
	{
		"id": 855,
		"phrase": "gusty"
	},
	{
		"id": 856,
		"phrase": "exotic"
	},
	{
		"id": 857,
		"phrase": "refuse"
	},
	{
		"id": 858,
		"phrase": "parsimonious"
	},
	{
		"id": 859,
		"phrase": "curly"
	},
	{
		"id": 860,
		"phrase": "bat"
	},
	{
		"id": 861,
		"phrase": "plate"
	},
	{
		"id": 862,
		"phrase": "carry"
	},
	{
		"id": 863,
		"phrase": "arrive"
	},
	{
		"id": 864,
		"phrase": "nerve"
	},
	{
		"id": 865,
		"phrase": "lively"
	},
	{
		"id": 866,
		"phrase": "finger"
	},
	{
		"id": 867,
		"phrase": "dirty"
	},
	{
		"id": 868,
		"phrase": "beautiful"
	},
	{
		"id": 869,
		"phrase": "applaud"
	},
	{
		"id": 870,
		"phrase": "wilderness"
	},
	{
		"id": 871,
		"phrase": "afford"
	},
	{
		"id": 872,
		"phrase": "jolly"
	},
	{
		"id": 873,
		"phrase": "hospitable"
	},
	{
		"id": 874,
		"phrase": "entertain"
	},
	{
		"id": 875,
		"phrase": "airplane"
	},
	{
		"id": 876,
		"phrase": "chin"
	},
	{
		"id": 877,
		"phrase": "pretty"
	},
	{
		"id": 878,
		"phrase": "scarce"
	},
	{
		"id": 879,
		"phrase": "grubby"
	},
	{
		"id": 880,
		"phrase": "slap"
	},
	{
		"id": 881,
		"phrase": "guitar"
	},
	{
		"id": 882,
		"phrase": "pricey"
	},
	{
		"id": 883,
		"phrase": "alcoholic"
	},
	{
		"id": 884,
		"phrase": "sky"
	},
	{
		"id": 885,
		"phrase": "distribution"
	},
	{
		"id": 886,
		"phrase": "ablaze"
	},
	{
		"id": 887,
		"phrase": "cloistered"
	},
	{
		"id": 888,
		"phrase": "shaky"
	},
	{
		"id": 889,
		"phrase": "opposite"
	},
	{
		"id": 890,
		"phrase": "caption"
	},
	{
		"id": 891,
		"phrase": "uninterested"
	},
	{
		"id": 892,
		"phrase": "cabbage"
	},
	{
		"id": 893,
		"phrase": "decide"
	},
	{
		"id": 894,
		"phrase": "flowers"
	},
	{
		"id": 895,
		"phrase": "kiss"
	},
	{
		"id": 896,
		"phrase": "part"
	},
	{
		"id": 897,
		"phrase": "nifty"
	},
	{
		"id": 898,
		"phrase": "scold"
	},
	{
		"id": 899,
		"phrase": "cakes"
	},
	{
		"id": 900,
		"phrase": "well-groomed"
	},
	{
		"id": 901,
		"phrase": "coordinated"
	},
	{
		"id": 902,
		"phrase": "distance"
	},
	{
		"id": 903,
		"phrase": "misty"
	},
	{
		"id": 904,
		"phrase": "fade"
	},
	{
		"id": 905,
		"phrase": "brother"
	},
	{
		"id": 906,
		"phrase": "nondescript"
	},
	{
		"id": 907,
		"phrase": "abhorrent"
	},
	{
		"id": 908,
		"phrase": "aboriginal"
	},
	{
		"id": 909,
		"phrase": "queue"
	},
	{
		"id": 910,
		"phrase": "file"
	},
	{
		"id": 911,
		"phrase": "fearless"
	},
	{
		"id": 912,
		"phrase": "jog"
	},
	{
		"id": 913,
		"phrase": "oranges"
	},
	{
		"id": 914,
		"phrase": "word"
	},
	{
		"id": 915,
		"phrase": "vacuous"
	},
	{
		"id": 916,
		"phrase": "rock"
	},
	{
		"id": 917,
		"phrase": "blind"
	},
	{
		"id": 918,
		"phrase": "driving"
	},
	{
		"id": 919,
		"phrase": "modern"
	},
	{
		"id": 920,
		"phrase": "robin"
	},
	{
		"id": 921,
		"phrase": "heavy"
	},
	{
		"id": 922,
		"phrase": "lamp"
	},
	{
		"id": 923,
		"phrase": "loud"
	},
	{
		"id": 924,
		"phrase": "simplistic"
	},
	{
		"id": 925,
		"phrase": "soup"
	},
	{
		"id": 926,
		"phrase": "letter"
	},
	{
		"id": 927,
		"phrase": "drown"
	},
	{
		"id": 928,
		"phrase": "ruddy"
	},
	{
		"id": 929,
		"phrase": "bewildered"
	},
	{
		"id": 930,
		"phrase": "abusive"
	},
	{
		"id": 931,
		"phrase": "punch"
	},
	{
		"id": 932,
		"phrase": "brief"
	},
	{
		"id": 933,
		"phrase": "sophisticated"
	},
	{
		"id": 934,
		"phrase": "fantastic"
	},
	{
		"id": 935,
		"phrase": "pot"
	},
	{
		"id": 936,
		"phrase": "sheep"
	},
	{
		"id": 937,
		"phrase": "hand"
	},
	{
		"id": 938,
		"phrase": "youthful"
	},
	{
		"id": 939,
		"phrase": "wax"
	},
	{
		"id": 940,
		"phrase": "bang"
	},
	{
		"id": 941,
		"phrase": "inject"
	},
	{
		"id": 942,
		"phrase": "subsequent"
	},
	{
		"id": 943,
		"phrase": "save"
	},
	{
		"id": 944,
		"phrase": "unaccountable"
	},
	{
		"id": 945,
		"phrase": "slip"
	},
	{
		"id": 946,
		"phrase": "vegetable"
	},
	{
		"id": 947,
		"phrase": "wrench"
	},
	{
		"id": 948,
		"phrase": "knowledge"
	},
	{
		"id": 949,
		"phrase": "blade"
	},
	{
		"id": 950,
		"phrase": "swim"
	},
	{
		"id": 951,
		"phrase": "cobweb"
	},
	{
		"id": 952,
		"phrase": "kitty"
	},
	{
		"id": 953,
		"phrase": "encouraging"
	},
	{
		"id": 954,
		"phrase": "beds"
	},
	{
		"id": 955,
		"phrase": "crash"
	},
	{
		"id": 956,
		"phrase": "tease"
	},
	{
		"id": 957,
		"phrase": "vast"
	},
	{
		"id": 958,
		"phrase": "umbrella"
	},
	{
		"id": 959,
		"phrase": "safe"
	},
	{
		"id": 960,
		"phrase": "zephyr"
	},
	{
		"id": 961,
		"phrase": "funny"
	},
	{
		"id": 962,
		"phrase": "strip"
	},
	{
		"id": 963,
		"phrase": "care"
	},
	{
		"id": 964,
		"phrase": "admire"
	},
	{
		"id": 965,
		"phrase": "guttural"
	},
	{
		"id": 966,
		"phrase": "thinkable"
	},
	{
		"id": 967,
		"phrase": "curve"
	},
	{
		"id": 968,
		"phrase": "question"
	},
	{
		"id": 969,
		"phrase": "afraid"
	},
	{
		"id": 970,
		"phrase": "seashore"
	},
	{
		"id": 971,
		"phrase": "honorable"
	},
	{
		"id": 972,
		"phrase": "gifted"
	},
	{
		"id": 973,
		"phrase": "interesting"
	},
	{
		"id": 974,
		"phrase": "level"
	},
	{
		"id": 975,
		"phrase": "tray"
	},
	{
		"id": 976,
		"phrase": "rose"
	},
	{
		"id": 977,
		"phrase": "four"
	},
	{
		"id": 978,
		"phrase": "dead"
	},
	{
		"id": 979,
		"phrase": "dust"
	},
	{
		"id": 980,
		"phrase": "crazy"
	},
	{
		"id": 981,
		"phrase": "careless"
	},
	{
		"id": 982,
		"phrase": "desire"
	},
	{
		"id": 983,
		"phrase": "trousers"
	},
	{
		"id": 984,
		"phrase": "ship"
	},
	{
		"id": 985,
		"phrase": "female"
	},
	{
		"id": 986,
		"phrase": "psychedelic"
	},
	{
		"id": 987,
		"phrase": "stay"
	},
	{
		"id": 988,
		"phrase": "fresh"
	},
	{
		"id": 989,
		"phrase": "clammy"
	},
	{
		"id": 990,
		"phrase": "gabby"
	},
	{
		"id": 991,
		"phrase": "damage"
	},
	{
		"id": 992,
		"phrase": "thought"
	},
	{
		"id": 993,
		"phrase": "incandescent"
	},
	{
		"id": 994,
		"phrase": "fear"
	},
	{
		"id": 995,
		"phrase": "odd"
	},
	{
		"id": 996,
		"phrase": "hug"
	},
	{
		"id": 997,
		"phrase": "worthless"
	},
	{
		"id": 998,
		"phrase": "reduce"
	},
	{
		"id": 999,
		"phrase": "baby"
	},
	{
		"id": 1000,
		"phrase": "paper"
	}
]